ocrodjvu/__init__.py
ocrodjvu/__main__.py
ocrodjvu/errors.py
ocrodjvu/hocr.py
ocrodjvu/html5_support.py
ocrodjvu/image_io.py
ocrodjvu/ipc.py
ocrodjvu/iso639.py
ocrodjvu/logger.py
ocrodjvu/temporary.py
ocrodjvu/text_zones.py
ocrodjvu/unicode_support.py
ocrodjvu/utils.py
ocrodjvu/version.py
ocrodjvu/cli/__init__.py
ocrodjvu/cli/djvu2hocr.py
ocrodjvu/cli/hocr2djvused.py
ocrodjvu/cli/ocrodjvu.py
ocrodjvu/engines/__init__.py
ocrodjvu/engines/common.py
ocrodjvu/engines/cuneiform.py
ocrodjvu/engines/dummy.py
ocrodjvu/engines/gocr.py
ocrodjvu/engines/ocrad.py
ocrodjvu/engines/tesseract.py
ocrodjvu-0.14.dist-info/COPYING
ocrodjvu-0.14.dist-info/METADATA
ocrodjvu-0.14.dist-info/WHEEL
ocrodjvu-0.14.dist-info/entry_points.txt
ocrodjvu-0.14.dist-info/top_level.txt
ocrodjvu-0.14.dist-info/RECORD
