Metadata-Version: 2.1
Name: ocrodjvu
Version: 0.14
Summary: OCR for DjVu (Python 3 fork)
Home-page: https://github.com/FriedrichFroebel/ocrodjvu/
Author: Jakub Wilk, FriedrichFröbel (Python 3)
License: GNU GPL 2
Classifier: Development Status :: 4 - Beta
Classifier: Environment :: Console
Classifier: Intended Audience :: End Users/Desktop
Classifier: License :: OSI Approved :: GNU General Public License (GPL)
Classifier: Operating System :: OS Independent
Classifier: Programming Language :: Python
Classifier: Programming Language :: Python :: 3
Classifier: Programming Language :: Python :: 3 :: Only
Classifier: Topic :: Text Processing
Classifier: Topic :: Multimedia :: Graphics
Requires-Python: >=3.6, <4
License-File: COPYING
Requires-Dist: djvulibre-python>=0.9
Requires-Dist: lxml>=2.0
Provides-Extra: dev
Requires-Dist: coverage; extra == "dev"
Requires-Dist: flake8; extra == "dev"
Requires-Dist: pep8-naming; extra == "dev"
Requires-Dist: Pillow; extra == "dev"
Provides-Extra: docs
Requires-Dist: docutils; extra == "docs"
Requires-Dist: pygments; extra == "docs"
